condensing/__init__.py
condensing/condensing.py
condensing-0.1.0.dist-info/METADATA
condensing-0.1.0.dist-info/WHEEL
condensing-0.1.0.dist-info/entry_points.txt
condensing-0.1.0.dist-info/top_level.txt
condensing-0.1.0.dist-info/RECORD
